llemming/__init__.py
llemming/analyze_directory.py
llemming/cli.py
llemming/settings.py
llemming/version.py
llemming/version.txt
llemming-0.0.2.dist-info/LICENSE
llemming-0.0.2.dist-info/METADATA
llemming-0.0.2.dist-info/WHEEL
llemming-0.0.2.dist-info/entry_points.txt
llemming-0.0.2.dist-info/top_level.txt
llemming-0.0.2.dist-info/RECORD
